[
  {
    "id": "up-0003",
    "handle": "@DF_TechDesk",
    "xUrl": "https://x.com/DF_TechDesk",
    "avatar": "https://images.unsplash.com/photo-1520975869018-5e0f9f2a6319?auto=format&fit=crop&w=120&q=70",
    "time": "13:41",
    "text": "Segnali su supply chain: attenzione a componentistica e lead time. Incrociamo conferme su canali primari.",
    "topic": "tecnologia",
    "ts": "2026-01-15T13:41:00+01:00"
  },
  {
    "id": "up-0002",
    "handle": "@DF_GeoDesk",
    "xUrl": "https://x.com/DF_GeoDesk",
    "avatar": "https://images.unsplash.com/photo-1520975916090-3105956dac38?auto=format&fit=crop&w=120&q=70",
    "time": "13:18",
    "text": "Brief: aumento frizione su corridoi logistici secondari. Possibile impatto su tempi e assicurazioni nel breve.",
    "topic": "geopolitica",
    "ts": "2026-01-15T13:18:00+01:00"
  },
  {
    "id": "up-0001",
    "handle": "@DarkFeedHQ",
    "xUrl": "https://x.com/DarkFeedHQ",
    "avatar": "https://images.unsplash.com/photo-1520975963131-2bdc9c79f2a2?auto=format&fit=crop&w=120&q=70",
    "time": "13:02",
    "text": "Monitoriamo evoluzione scenario: primi segnali di repricing su risk premia. Update appena confermiamo i dettagli.",
    "topic": "finanza",
    "ts": "2026-01-15T13:02:00+01:00"
  }
]
